{
  "type": "minecraft:chest",
  "pools": [
    {
      "rolls": {
        "min": 1.0,
        "max": 3.0,
        "type": "minecraft:uniform"
      },
      "entries": [
        {
          "weight": 5,
          "type": "minecraft:loot_table",
          "value": "yungsbettertfc:shared/equipment/dangerous/sword"
        },
        {
          "weight": 2,
          "type": "minecraft:loot_table",
          "value": "yungsbettertfc:shared/equipment/dangerous/sword",
          "functions": [
            {
              "function": "minecraft:enchant_with_levels",
              "options": "#minecraft:on_random_loot",
              "levels": 10.0
            }
          ]
        },
        {
          "weight": 5,
          "type": "minecraft:loot_table",
          "value": "yungsbettertfc:shared/equipment/dangerous/sword"
        },
        {
          "weight": 1,
          "type": "minecraft:loot_table",
          "value": "yungsbettertfc:shared/equipment/dangerous/sword",
          "functions": [
            {
              "function": "minecraft:enchant_with_levels",
              "options": "#minecraft:on_random_loot",
              "levels": 20.0
            }
          ]
        },
        {
          "weight": 1,
          "type": "minecraft:loot_table",
          "value": "yungsbettertfc:shared/equipment/dangerous/sword"
        },
        {
          "weight": 1,
          "type": "minecraft:loot_table",
          "value": "yungsbettertfc:shared/equipment/dangerous/sword",
          "functions": [
            {
              "function": "minecraft:enchant_with_levels",
              "options": "#minecraft:on_random_loot",
              "levels": 30.0
            }
          ]
        },
        {
          "weight": 5,
          "type": "minecraft:loot_table",
          "value": "yungsbettertfc:shared/equipment/dangerous/helmet"
        },
        {
          "weight": 5,
          "type": "minecraft:loot_table",
          "value": "yungsbettertfc:shared/equipment/dangerous/chestplate"
        },
        {
          "weight": 5,
          "type": "minecraft:loot_table",
          "value": "yungsbettertfc:shared/equipment/dangerous/leggings"
        },
        {
          "weight": 5,
          "type": "minecraft:loot_table",
          "value": "yungsbettertfc:shared/equipment/dangerous/boots"
        },
        {
          "weight": 3,
          "type": "minecraft:loot_table",
          "value": "yungsbettertfc:shared/equipment/dangerous/helmet"
        },
        {
          "weight": 3,
          "type": "minecraft:loot_table",
          "value": "yungsbettertfc:shared/equipment/dangerous/chestplate"
        },
        {
          "weight": 3,
          "type": "minecraft:loot_table",
          "value": "yungsbettertfc:shared/equipment/dangerous/leggings"
        },
        {
          "weight": 3,
          "type": "minecraft:loot_table",
          "value": "yungsbettertfc:shared/equipment/dangerous/boots"
        },
        {
          "weight": 5,
          "type": "minecraft:loot_table",
          "value": "yungsbettertfc:shared/equipment/dangerous/helmet"
        },
        {
          "weight": 1,
          "type": "minecraft:loot_table",
          "value": "yungsbettertfc:shared/equipment/dangerous/helmet",
          "functions": [
            {
              "function": "minecraft:enchant_with_levels",
              "options": "#minecraft:on_random_loot",
              "levels": 20.0
            }
          ]
        },
        {
          "weight": 5,
          "type": "minecraft:loot_table",
          "value": "yungsbettertfc:shared/equipment/dangerous/chestplate"
        },
        {
          "weight": 1,
          "type": "minecraft:loot_table",
          "value": "yungsbettertfc:shared/equipment/dangerous/chestplate",
          "functions": [
            {
              "function": "minecraft:enchant_with_levels",
              "options": "#minecraft:on_random_loot",
              "levels": 20.0
            }
          ]
        },
        {
          "weight": 5,
          "type": "minecraft:loot_table",
          "value": "yungsbettertfc:shared/equipment/dangerous/leggings"
        },
        {
          "weight": 1,
          "type": "minecraft:loot_table",
          "value": "yungsbettertfc:shared/equipment/dangerous/leggings",
          "functions": [
            {
              "function": "minecraft:enchant_with_levels",
              "options": "#minecraft:on_random_loot",
              "levels": 20.0
            }
          ]
        },
        {
          "weight": 5,
          "type": "minecraft:loot_table",
          "value": "yungsbettertfc:shared/equipment/dangerous/boots"
        },
        {
          "weight": 1,
          "type": "minecraft:loot_table",
          "value": "yungsbettertfc:shared/equipment/dangerous/boots",
          "functions": [
            {
              "function": "minecraft:enchant_with_levels",
              "options": "#minecraft:on_random_loot",
              "levels": 20.0
            }
          ]
        },
        {
          "weight": 1,
          "type": "minecraft:loot_table",
          "value": "yungsbettertfc:shared/equipment/dangerous/helmet"
        },
        {
          "weight": 1,
          "type": "minecraft:loot_table",
          "value": "yungsbettertfc:shared/equipment/dangerous/helmet",
          "functions": [
            {
              "function": "minecraft:enchant_with_levels",
              "options": "#minecraft:on_random_loot",
              "levels": 30.0
            }
          ]
        },
        {
          "weight": 1,
          "type": "minecraft:loot_table",
          "value": "yungsbettertfc:shared/equipment/dangerous/chestplate"
        },
        {
          "weight": 1,
          "type": "minecraft:loot_table",
          "value": "yungsbettertfc:shared/equipment/dangerous/chestplate",
          "functions": [
            {
              "function": "minecraft:enchant_with_levels",
              "options": "#minecraft:on_random_loot",
              "levels": 30.0
            }
          ]
        },
        {
          "weight": 1,
          "type": "minecraft:loot_table",
          "value": "yungsbettertfc:shared/equipment/dangerous/leggings"
        },
        {
          "weight": 1,
          "type": "minecraft:loot_table",
          "value": "yungsbettertfc:shared/equipment/dangerous/leggings",
          "functions": [
            {
              "function": "minecraft:enchant_with_levels",
              "options": "#minecraft:on_random_loot",
              "levels": 30.0
            }
          ]
        },
        {
          "weight": 1,
          "type": "minecraft:loot_table",
          "value": "yungsbettertfc:shared/equipment/dangerous/boots"
        },
        {
          "weight": 1,
          "type": "minecraft:loot_table",
          "value": "yungsbettertfc:shared/equipment/dangerous/boots",
          "functions": [
            {
              "function": "minecraft:enchant_with_levels",
              "options": "#minecraft:on_random_loot",
              "levels": 30.0
            }
          ]
        },
        {
          "weight": 6,
          "type": "minecraft:loot_table",
          "value": "yungsbettertfc:shared/equipment/dangerous/shield"
        },
        {
          "weight": 5,
          "type": "minecraft:loot_table",
          "value": "yungsbettertfc:shared/equipment/dangerous/bow"
        },
        {
          "weight": 1,
          "type": "minecraft:loot_table",
          "value": "yungsbettertfc:shared/equipment/dangerous/bow",
          "functions": [
            {
              "function": "minecraft:enchant_with_levels",
              "options": "#minecraft:on_random_loot",
              "levels": 30.0
            }
          ]
        },
        {
          "weight": 7,
          "type": "minecraft:loot_table",
          "value": "yungsbettertfc:shared/coal_like",
          "functions": [
            {
              "function": "minecraft:set_count",
              "count": {
                "min": 2.0,
                "max": 7.0,
                "type": "minecraft:uniform"
              }
            }
          ]
        },
        {
          "weight": 7,
          "type": "minecraft:loot_table",
          "value": "yungsbettertfc:shared/coal_like",
          "functions": [
            {
              "function": "minecraft:set_count",
              "count": {
                "min": 2.0,
                "max": 7.0,
                "type": "minecraft:uniform"
              }
            }
          ]
        }
      ]
    }
  ]
}
